README.txt
bootstrap.py
buildout.cfg
setup.py
collective/__init__.py
collective.dewplayer.egg-info/PKG-INFO
collective.dewplayer.egg-info/SOURCES.txt
collective.dewplayer.egg-info/dependency_links.txt
collective.dewplayer.egg-info/entry_points.txt
collective.dewplayer.egg-info/namespace_packages.txt
collective.dewplayer.egg-info/not-zip-safe
collective.dewplayer.egg-info/requires.txt
collective.dewplayer.egg-info/top_level.txt
collective/dewplayer/__init__.py
collective/dewplayer/configure.zcml
collective/dewplayer/interfaces.py
collective/dewplayer/upgrades.py
collective/dewplayer/upgrades.zcml
collective/dewplayer/browser/__init__.py
collective/dewplayer/browser/base.py
collective/dewplayer/browser/configure.zcml
collective/dewplayer/browser/dewplayer.pt
collective/dewplayer/browser/file.py
collective/dewplayer/browser/folder.py
collective/dewplayer/browser/itemview.pt
collective/dewplayer/browser/itemview.py
collective/dewplayer/browser/link.py
collective/dewplayer/browser/playlist.pt
collective/dewplayer/browser/playlist.py
collective/dewplayer/browser/topic.py
collective/dewplayer/browser/dewplayer/README.txt
collective/dewplayer/browser/dewplayer/dewplayer-bubble.swf
collective/dewplayer/browser/dewplayer/dewplayer-mini.swf
collective/dewplayer/browser/dewplayer/dewplayer-multi.swf
collective/dewplayer/browser/dewplayer/dewplayer-playlist-cover.swf
collective/dewplayer/browser/dewplayer/dewplayer-playlist.swf
collective/dewplayer/browser/dewplayer/dewplayer-rect.swf
collective/dewplayer/browser/dewplayer/dewplayer-stream.swf
collective/dewplayer/browser/dewplayer/dewplayer-vinyl.swf
collective/dewplayer/browser/dewplayer/dewplayer-vol.swf
collective/dewplayer/browser/dewplayer/dewplayer.swf
collective/dewplayer/profiles/default/metadata.xml
collective/dewplayer/profiles/default/types.xml
collective/dewplayer/profiles/default/types/File.xml
collective/dewplayer/profiles/default/types/Folder.xml
collective/dewplayer/profiles/default/types/Link.xml
collective/dewplayer/profiles/default/types/Topic.xml
docs/HISTORY.txt