Metadata-Version: 1.0
Name: collective.dewplayer
Version: 1.2
Summary: A simple package using Dewplayer for video content - By Makina Corpus
Home-page: http://svn.plone.org/svn/collective/collective.dewplayer/trunk
Author: Sylvain BOURELIOU
Author-email: sylvain.boureliou@makina-corpus.com
License: GPL
Keywords: Plone Python Dewplayer
Platform: UNKNOWN
Classifier: Programming Language :: Python
